MANIFEST.in
README.md
setup.py
service_registry/__init__.py
service_registry/base.py
service_registry/client.py
service_registry/constants.py
service_registry/errors.py
service_registry/heartbeater.py
service_registry.egg-info/PKG-INFO
service_registry.egg-info/SOURCES.txt
service_registry.egg-info/dependency_links.txt
service_registry.egg-info/requires.txt
service_registry.egg-info/top_level.txt
service_registry/test/__init__.py
service_registry/test/mock_http_server.py
service_registry/test/test_client.py
service_registry/test/utils.py
utils/__init__.py
utils/dist.py